chemllmhack/__init__.py
chemllmhack/benchmark/benchmark_RMSD/benchmark_protein.pdb
chemllmhack/benchmark/benchmark_affinity/benchmark_affinity_M.json
chemllmhack/benchmark/benchmark_affinity/benchmark_affinity_wT.json
chemllmhack/calc_stats_vs_benchmark.py
chemllmhack/demo/langchain_research_agent.py
chemllmhack/demo/paper_db/chroma_db/chroma.sqlite3
chemllmhack/demo/project/project_id.txt
chemllmhack/demo/project/simulated.pdb
chemllmhack/demo/project/test_benchmark.json
chemllmhack/demo/result_dir/13201921-7096-430c-8fde-2558f07a1a7d.json
chemllmhack/demo/result_dir/6c2b4db5-a9bc-42db-8735-834fc54226b3.json
chemllmhack/demo/result_dir/84bd2da5-0c76-4b4c-a0e9-c899d9bc32fc.json
chemllmhack/demo/result_dir/f1374067-3c07-4e04-8980-a8fa7ca06b9b.json
chemllmhack/rag_toolkit.py
chemllmhack/rex_expressions.json
chemllmhack/rex_language.py
chemllmhack/temp/BTKbindingData.xlsx
chemllmhack/temp/test.py
chemllmhack/temp/xls2json.py
chemllmhack/test_atlas.py
chemllmhack/utility/xls2json.py
chemllmhack-0.1.9.dist-info/METADATA
chemllmhack-0.1.9.dist-info/WHEEL
chemllmhack-0.1.9.dist-info/entry_points.txt
chemllmhack-0.1.9.dist-info/RECORD
