Metadata-Version: 2.1
Name: chemllmhack
Version: 0.1.9
Summary: A SDK for computational chemistry LLM hackthon
Author: bowen zhang
Author-email: bowen.zhang@qdx.co
Requires-Python: >=3.11,<3.13
Classifier: Programming Language :: Python :: 3
Classifier: Programming Language :: Python :: 3.11
Classifier: Programming Language :: Python :: 3.12
Requires-Dist: biopython (>=1.84,<2.0)
Requires-Dist: google-cloud-storage (>=2.17.0,<3.0.0)
Requires-Dist: langchain (>=0.2.8,<0.3.0)
Requires-Dist: langchain-chroma (>=0.1.2,<0.2.0)
Requires-Dist: langchain-community (>=0.2.7,<0.3.0)
Requires-Dist: langchain-mongodb (>=0.1.6,<0.2.0)
Requires-Dist: langchain-openai (>=0.1.16,<0.2.0)
Requires-Dist: langchainhub (>=0.1.20,<0.2.0)
Requires-Dist: langgraph (>=0.1.9,<0.2.0)
Requires-Dist: openpyxl (>=3.1.5,<4.0.0)
Requires-Dist: pandas (>=2.2.2,<3.0.0)
Requires-Dist: pymongo[srv] (>=4.8.0,<5.0.0)
Requires-Dist: pymupdf (>=1.24.7,<2.0.0)
Requires-Dist: pypdf (>=4.3.0,<5.0.0)
Requires-Dist: requests (>=2.32.3,<3.0.0)
Requires-Dist: scipy (>=1.14.0,<2.0.0)
